neural_network_model/VERSION
neural_network_model/__init__.py
neural_network_model/bit_vision.py
neural_network_model/model.py
neural_network_model/plot_results.py
neural_network_model/process_data.py
neural_network_model/s3.py
neural_network_model/script_run_all.py
neural_network_model/transfer_learning.py
neural_network_model/visual_insights.py
drillvision-1.1.0.dist-info/METADATA
drillvision-1.1.0.dist-info/WHEEL
drillvision-1.1.0.dist-info/top_level.txt
drillvision-1.1.0.dist-info/RECORD
