Metadata-Version: 2.1
Name: drillvision
Version: 1.1.0
Summary: DrillBitVision
Home-page: https://github.com/Atashnezhad/DrillBitVision
Author: Amin Atashnezhad
Author-email: atashnezhad2@gmail.com
License: BSD-3
Platform: UNKNOWN
Classifier: License :: OSI Approved :: MIT License
Classifier: Programming Language :: Python
Classifier: Programming Language :: Python :: 3.9
Requires-Python: >=3.9.0
Requires-Dist: requests ==2.30.0
Requires-Dist: bs4 ==0.0.1
Requires-Dist: bing-image-downloader
Requires-Dist: pillow ==9.5.0
Requires-Dist: pydantic ~=1.10.7
Requires-Dist: tqdm ~=4.65.0
Requires-Dist: matplotlib ~=3.7.1
Requires-Dist: tensorflow ~=2.12.0
Requires-Dist: numpy ~=1.23.5
Requires-Dist: keras ~=2.12.0
Requires-Dist: pandas ~=2.0.1
Requires-Dist: IPython ~=8.13.2
Requires-Dist: pytest ~=7.3.1
Requires-Dist: pathlib
Requires-Dist: boto3 ~=1.26.137
Requires-Dist: python-dotenv ~=1.0.0
Requires-Dist: seaborn ~=0.11.2
Requires-Dist: scikit-learn ==1.2.2
Requires-Dist: imageio ==2.31.0
Requires-Dist: opencv-python ==4.8.0.74
Requires-Dist: scikit-image ==0.21.0
